pspring/__init__.py
pspring/pspring.py
pspring/core/autowired.py
pspring/core/bean.py
pspring/core/cacheprovider.py
pspring/core/config.py
pspring/core/configprovider.py
pspring/core/context.py
pspring/core/jsonconfigprovider.py
pspring-0.0.39.dist-info/LICENSE
pspring-0.0.39.dist-info/METADATA
pspring-0.0.39.dist-info/WHEEL
pspring-0.0.39.dist-info/top_level.txt
pspring-0.0.39.dist-info/RECORD
