Metadata-Version: 2.1
Name: pspring
Version: 0.0.39
Summary: A framework inspired by spring for python
Home-page: https://github.com/vasudevan-palani/pspring
Author: Vasudevan Palani
Author-email: vasudevan.palani@gmail.com
License: TBD
Platform: UNKNOWN
